Metadata-Version: 2.1
Name: JsrBotsIG
Version: 0.0.2
Summary: JSR Bots Instagram API
Home-page: 
Author: JSR Bots
Author-email: jsrbots@gmail.com
License: MIT
Keywords: instagram,instagrapi,instagramapi,api,instagramlogin,instaapi
Classifier: Development Status :: 5 - Production/Stable
Classifier: Intended Audience :: Education
Classifier: Operating System :: Microsoft :: Windows :: Windows 10
Classifier: License :: OSI Approved :: MIT License
Classifier: Programming Language :: Python :: 3
License-File: LICENSE.txt
